iflow_mcp_hepivax_mcp_as_a_judge/__init__.py
iflow_mcp_hepivax_mcp_as_a_judge/models.py
iflow_mcp_hepivax_mcp_as_a_judge/server.py
iflow_mcp_hepivax_mcp_as_a_judge/core/__init__.py
iflow_mcp_hepivax_mcp_as_a_judge/core/constants.py
iflow_mcp_hepivax_mcp_as_a_judge/core/logging_config.py
iflow_mcp_hepivax_mcp_as_a_judge/core/server_helpers.py
iflow_mcp_hepivax_mcp_as_a_judge/db/__init__.py
iflow_mcp_hepivax_mcp_as_a_judge/db/cleanup_service.py
iflow_mcp_hepivax_mcp_as_a_judge/db/conversation_history_service.py
iflow_mcp_hepivax_mcp_as_a_judge/db/db_config.py
iflow_mcp_hepivax_mcp_as_a_judge/db/dynamic_token_limits.py
iflow_mcp_hepivax_mcp_as_a_judge/db/factory.py
iflow_mcp_hepivax_mcp_as_a_judge/db/interface.py
iflow_mcp_hepivax_mcp_as_a_judge/db/token_utils.py
iflow_mcp_hepivax_mcp_as_a_judge/db/providers/__init__.py
iflow_mcp_hepivax_mcp_as_a_judge/db/providers/sqlite_provider.py
iflow_mcp_hepivax_mcp_as_a_judge/elicitation/__init__.py
iflow_mcp_hepivax_mcp_as_a_judge/elicitation/factory.py
iflow_mcp_hepivax_mcp_as_a_judge/elicitation/fallback_provider.py
iflow_mcp_hepivax_mcp_as_a_judge/elicitation/interface.py
iflow_mcp_hepivax_mcp_as_a_judge/elicitation/mcp_provider.py
iflow_mcp_hepivax_mcp_as_a_judge/llm/__init__.py
iflow_mcp_hepivax_mcp_as_a_judge/llm/llm_client.py
iflow_mcp_hepivax_mcp_as_a_judge/llm/llm_integration.py
iflow_mcp_hepivax_mcp_as_a_judge/messaging/__init__.py
iflow_mcp_hepivax_mcp_as_a_judge/messaging/converters.py
iflow_mcp_hepivax_mcp_as_a_judge/messaging/factory.py
iflow_mcp_hepivax_mcp_as_a_judge/messaging/interface.py
iflow_mcp_hepivax_mcp_as_a_judge/messaging/llm_api_provider.py
iflow_mcp_hepivax_mcp_as_a_judge/messaging/llm_provider.py
iflow_mcp_hepivax_mcp_as_a_judge/messaging/mcp_sampling_provider.py
iflow_mcp_hepivax_mcp_as_a_judge/models/__init__.py
iflow_mcp_hepivax_mcp_as_a_judge/models/enhanced_responses.py
iflow_mcp_hepivax_mcp_as_a_judge/models/task_metadata.py
iflow_mcp_hepivax_mcp_as_a_judge/prompting/__init__.py
iflow_mcp_hepivax_mcp_as_a_judge-0.5.0.dist-info/METADATA
iflow_mcp_hepivax_mcp_as_a_judge-0.5.0.dist-info/WHEEL
iflow_mcp_hepivax_mcp_as_a_judge-0.5.0.dist-info/entry_points.txt
iflow_mcp_hepivax_mcp_as_a_judge-0.5.0.dist-info/licenses/LICENSE
iflow_mcp_hepivax_mcp_as_a_judge-0.5.0.dist-info/RECORD
